docketanalyzer_pacer/__init__.py
docketanalyzer_pacer/pacer.py
docketanalyzer_pacer/recap.py
docketanalyzer_pacer-0.1.1.dist-info/METADATA
docketanalyzer_pacer-0.1.1.dist-info/WHEEL
docketanalyzer_pacer-0.1.1.dist-info/licenses/LICENSE
docketanalyzer_pacer-0.1.1.dist-info/RECORD
